finbrain/__init__.py
finbrain/client.py
finbrain/exceptions.py
finbrain/plotting.py
finbrain/py.typed
finbrain/aio/__init__.py
finbrain/aio/client.py
finbrain/aio/endpoints/__init__.py
finbrain/aio/endpoints/_utils.py
finbrain/aio/endpoints/analyst_ratings.py
finbrain/aio/endpoints/app_ratings.py
finbrain/aio/endpoints/available.py
finbrain/aio/endpoints/house_trades.py
finbrain/aio/endpoints/insider_transactions.py
finbrain/aio/endpoints/linkedin_data.py
finbrain/aio/endpoints/options.py
finbrain/aio/endpoints/predictions.py
finbrain/aio/endpoints/senate_trades.py
finbrain/aio/endpoints/sentiments.py
finbrain/endpoints/__init__.py
finbrain/endpoints/_utils.py
finbrain/endpoints/analyst_ratings.py
finbrain/endpoints/app_ratings.py
finbrain/endpoints/available.py
finbrain/endpoints/house_trades.py
finbrain/endpoints/insider_transactions.py
finbrain/endpoints/linkedin_data.py
finbrain/endpoints/options.py
finbrain/endpoints/predictions.py
finbrain/endpoints/senate_trades.py
finbrain/endpoints/sentiments.py
finbrain_python-0.1.8.dist-info/licenses/LICENSE
finbrain_python-0.1.8.dist-info/METADATA
finbrain_python-0.1.8.dist-info/WHEEL
finbrain_python-0.1.8.dist-info/top_level.txt
finbrain_python-0.1.8.dist-info/RECORD
