Metadata-Version: 2.4
Name: finbrain-python
Version: 0.1.8
Summary: Official Python client for the FinBrain API
Author-email: Ahmet Salim Bilgin <ahmet@finbrain.tech>
License-Expression: MIT
Requires-Python: >=3.9
License-File: LICENSE
Requires-Dist: requests>=2.31
Requires-Dist: typer[all]>=0.12
Requires-Dist: pandas>=2.2
Requires-Dist: plotly>=6.0
Requires-Dist: numpy>=1.22.4
Provides-Extra: async
Requires-Dist: httpx>=0.24; extra == "async"
Provides-Extra: dev
Requires-Dist: pytest; extra == "dev"
Requires-Dist: pytest-asyncio; extra == "dev"
Requires-Dist: responses; extra == "dev"
Requires-Dist: httpx>=0.24; extra == "dev"
Requires-Dist: build; extra == "dev"
Requires-Dist: twine; extra == "dev"
Requires-Dist: ruff; extra == "dev"
Dynamic: license-file
